main.py
fclib/__init__.py
fclib/compound.py
test/__init__.py
test/test_compound.py
fclib-0.0.1.dist-info/LICENSE
fclib-0.0.1.dist-info/METADATA
fclib-0.0.1.dist-info/WHEEL
fclib-0.0.1.dist-info/top_level.txt
fclib-0.0.1.dist-info/zip-safe
fclib-0.0.1.dist-info/RECORD
