Metadata-Version: 2.1
Name: fclib
Version: 0.0.1
Summary: A financial computation library
Home-page: https://github.com/amgs/fclib
Author: André Sabino
Author-email: andre.sabino@gmail.com
License: BSD 3-Clause License
Platform: UNKNOWN
Classifier: Programming Language :: Python :: 3
Classifier: License :: OSI Approved :: BSD License
Classifier: Operating System :: OS Independent
Requires-Dist: scipy
